add2numbers_jamesbond/__init__.py
add2numbers_jamesbond/add.py
add2numbers_jamesbond-0.1.0.dist-info/WHEEL
add2numbers_jamesbond-0.1.0.dist-info/METADATA
add2numbers_jamesbond-0.1.0.dist-info/RECORD
